softener/__init__.py
softener/cli/__init__.py
softener/cli/cmds/__init__.py
softener/cli/cmds/debug.py
softener/cli/cmds/list.py
softener/cli/cmds/parse.py
softener/cli/cmds/path.py
softener/core/__init__.py
softener/core/app.py
softener/core/config.py
softener/core/format.py
softener/core/parse.py
softener/core/query.py
softener/data/schemas/config.json
softener/errors.py
softener-0.0.0b0.dist-info/entry_points.txt
softener-0.0.0b0.dist-info/LICENSE
softener-0.0.0b0.dist-info/WHEEL
softener-0.0.0b0.dist-info/METADATA
softener-0.0.0b0.dist-info/RECORD
